mesdf.cpython-312-darwin.so
mesdf-0.1.10.dist-info/RECORD
mesdf-0.1.10.dist-info/WHEEL
mesdf-0.1.10.dist-info/top_level.txt
mesdf-0.1.10.dist-info/LICENSE.txt
mesdf-0.1.10.dist-info/METADATA
